kakeibox_cli/__init__.py
kakeibox_cli/kakeibox.py
kakeibox_cli/commands/__init__.py
kakeibox_cli/commands/expenses/__init__.py
kakeibox_cli/commands/expenses/delete.py
kakeibox_cli/commands/expenses/get.py
kakeibox_cli/commands/expenses/new.py
kakeibox_cli/commands/expenses/total_period.py
kakeibox_cli/commands/expenses/update.py
kakeibox_cli/commands/incomes/__init__.py
kakeibox_cli/commands/incomes/delete.py
kakeibox_cli/commands/incomes/get.py
kakeibox_cli/commands/incomes/new.py
kakeibox_cli/commands/incomes/total_period.py
kakeibox_cli/commands/incomes/update.py
kakeibox_cli/commands/savings/__init__.py
kakeibox_cli/commands/savings/total_period.py
kakeibox_cli/commands/transaction_categories/__init__.py
kakeibox_cli/commands/transaction_categories/delete.py
kakeibox_cli/commands/transaction_categories/get.py
kakeibox_cli/commands/transaction_categories/list_all.py
kakeibox_cli/commands/transaction_categories/new.py
kakeibox_cli/commands/transaction_categories/update.py
kakeibox_cli/commands/transaction_subcategories/__init__.py
kakeibox_cli/commands/transaction_subcategories/delete.py
kakeibox_cli/commands/transaction_subcategories/get.py
kakeibox_cli/commands/transaction_subcategories/list_all.py
kakeibox_cli/commands/transaction_subcategories/list_per_category.py
kakeibox_cli/commands/transaction_subcategories/new.py
kakeibox_cli/commands/transaction_subcategories/update.py
kakeibox_cli/commands/transactions/__init__.py
kakeibox_cli/commands/transactions/list_all.py
kakeibox_cli-0.0.5.dist-info/AUTHORS.rst
kakeibox_cli-0.0.5.dist-info/LICENSE
kakeibox_cli-0.0.5.dist-info/METADATA
kakeibox_cli-0.0.5.dist-info/WHEEL
kakeibox_cli-0.0.5.dist-info/top_level.txt
kakeibox_cli-0.0.5.dist-info/RECORD
